{
  "config": {
    "configFile": "C:\\playwrightAutomationAssessment\\playwright.config.ts",
    "rootDir": "C:/playwrightAutomationAssessment/tests",
    "forbidOnly": false,
    "fullyParallel": true,
    "globalSetup": null,
    "globalTeardown": null,
    "globalTimeout": 0,
    "grep": {},
    "grepInvert": null,
    "maxFailures": 0,
    "metadata": {
      "actualWorkers": 1
    },
    "preserveOutput": "always",
    "reporter": [
      [
        "dot",
        null
      ],
      [
        "json",
        {
          "outputFile": "jsonReports/jsonReport.json"
        }
      ],
      [
        "html",
        {
          "open": "always"
        }
      ]
    ],
    "reportSlowTests": {
      "max": 5,
      "threshold": 300000
    },
    "quiet": false,
    "projects": [
      {
        "outputDir": "C:/playwrightAutomationAssessment/test-results",
        "repeatEach": 1,
        "retries": 0,
        "metadata": {
          "actualWorkers": 1
        },
        "id": "chromium",
        "name": "chromium",
        "testDir": "C:/playwrightAutomationAssessment/tests",
        "testIgnore": [],
        "testMatch": [
          "**/*.@(spec|test).?(c|m)[jt]s?(x)"
        ],
        "timeout": 30000
      }
    ],
    "shard": null,
    "updateSnapshots": "missing",
    "updateSourceMethod": "3way",
    "version": "1.51.0",
    "workers": 4,
    "webServer": null
  },
  "suites": [
    {
      "title": "validationJupiterPage-Fixture.spec.ts",
      "file": "validationJupiterPage-Fixture.spec.ts",
      "column": 0,
      "line": 0,
      "specs": [],
      "suites": [
        {
          "title": "Jupiter toy website validations",
          "file": "validationJupiterPage-Fixture.spec.ts",
          "line": 4,
          "column": 6,
          "specs": [
            {
              "title": "Contact Page validations testcase_01",
              "ok": true,
              "tags": [],
              "tests": [
                {
                  "timeout": 30000,
                  "annotations": [],
                  "expectedStatus": "passed",
                  "projectId": "chromium",
                  "projectName": "chromium",
                  "results": [
                    {
                      "workerIndex": 37,
                      "parallelIndex": 0,
                      "status": "passed",
                      "duration": 17379,
                      "errors": [],
                      "stdout": [],
                      "stderr": [],
                      "retry": 0,
                      "startTime": "2025-03-09T11:03:27.929Z",
                      "attachments": [
                        {
                          "name": "screenshot",
                          "contentType": "image/png",
                          "path": "C:\\playwrightAutomationAssessment\\test-results\\validationJupiterPage-Fixt-5b73a-age-validations-testcase-01-chromium\\test-finished-1.png"
                        }
                      ]
                    }
                  ],
                  "status": "expected"
                }
              ],
              "id": "60544c6bebdbc00d9f9c-b56b13ca29bbb8cfeba8",
              "file": "validationJupiterPage-Fixture.spec.ts",
              "line": 6,
              "column": 5
            }
          ]
        }
      ]
    }
  ],
  "errors": [],
  "stats": {
    "startTime": "2025-03-09T11:03:25.314Z",
    "duration": 21456.35899999994,
    "expected": 1,
    "skipped": 0,
    "unexpected": 0,
    "flaky": 0
  }
}